<?xml version="1.0" encoding="UTF-8"?>
<objects serializationModel="Studio.02.02.00">
	<object class="AudioFile" id="{1676b81b-6dd5-4a01-a25c-ded7e7799724}">
		<property name="assetPath">
			<value>LittleBoy-RocksAtPigeons2.wav</value>
		</property>
		<property name="frequencyInKHz">
			<value>44.0999985</value>
		</property>
		<property name="channelCount">
			<value>2</value>
		</property>
		<property name="length">
			<value>6.7679591836734696</value>
		</property>
		<relationship name="masterAssetFolder">
			<destination>{3ad85519-6323-4841-8cfb-6cde2b0a8d62}</destination>
		</relationship>
	</object>
</objects>
