<?xml version="1.0" encoding="UTF-8"?>
<objects serializationModel="Studio.02.02.00">
	<object class="AudioFile" id="{b501df8a-5c16-4104-836c-346097bc0568}">
		<property name="assetPath">
			<value>Weapons/Sword/Sword Miss/Sword Miss 5.wav</value>
		</property>
		<property name="frequencyInKHz">
			<value>44.0999985</value>
		</property>
		<property name="channelCount">
			<value>2</value>
		</property>
		<property name="length">
			<value>1.4800907029478458</value>
		</property>
		<relationship name="masterAssetFolder">
			<destination>{3ad85519-6323-4841-8cfb-6cde2b0a8d62}</destination>
		</relationship>
	</object>
</objects>
